SPARQL2Spark/ConstructResult.py
SPARQL2Spark/SelectResult.py
SPARQL2Spark/Wrapper.py
SPARQL2Spark/__init__.py
SPARQL2Spark-0.0.5.dist-info/DESCRIPTION.rst
SPARQL2Spark-0.0.5.dist-info/METADATA
SPARQL2Spark-0.0.5.dist-info/RECORD
SPARQL2Spark-0.0.5.dist-info/WHEEL
SPARQL2Spark-0.0.5.dist-info/metadata.json
SPARQL2Spark-0.0.5.dist-info/top_level.txt
