Metadata-Version: 2.0
Name: SPARQL2Spark
Version: 0.0.5
Summary: SPARQL Result to Spark
Home-page: UNKNOWN
Author: Emanuele Falzone
Author-email: emanuele.falzone@polimi.it
License: UNKNOWN
Platform: UNKNOWN
Classifier: Programming Language :: Python :: 3
Classifier: License :: OSI Approved :: MIT License
Classifier: Operating System :: OS Independent
Requires-Dist: graphframes
Requires-Dist: pyspark
Requires-Dist: rdflib
Requires-Dist: rdflib-jsonld
Requires-Dist: sparqlwrapper
